nonebot_plugin_eventdone/.gitignore
nonebot_plugin_eventdone/__init__.py
nonebot_plugin_eventdone/config.py
nonebot_plugin_eventdone/README.md
nonebot_plugin_eventdone/set.json
nonebot_plugin_eventdone-1.1.1.dist-info/LICENSE
nonebot_plugin_eventdone-1.1.1.dist-info/WHEEL
nonebot_plugin_eventdone-1.1.1.dist-info/METADATA
nonebot_plugin_eventdone-1.1.1.dist-info/RECORD
