Metadata-Version: 2.1
Name: nonebot-plugin-eventdone
Version: 1.1.1
Summary: 
License: MIT
Author: Padro Felice
Author-email: 2659737583@qq.com
Requires-Python: >=3.8,<4.0
Classifier: License :: OSI Approved :: MIT License
Classifier: Programming Language :: Python :: 3
Classifier: Programming Language :: Python :: 3.10
Classifier: Programming Language :: Python :: 3.8
Classifier: Programming Language :: Python :: 3.9
Requires-Dist: aiofiles (>=23.1.0,<24.0.0)
Requires-Dist: nonebot-adapter-onebot (>=2.1.3,<3.0.0)
Requires-Dist: nonebot2 (>=2.0.0-rc.3,<3.0.0)
